<?xml version="1.0" encoding="UTF-8"?>
<objects serializationModel="Studio.02.02.00">
	<object class="AudioFile" id="{43fa954d-6dfa-4794-9c9a-780c00dda368}">
		<property name="assetPath">
			<value>SUI0_TitleBtn.mp3</value>
		</property>
		<property name="frequencyInKHz">
			<value>44.0999985</value>
		</property>
		<property name="channelCount">
			<value>2</value>
		</property>
		<property name="length">
			<value>5.6946938775510203</value>
		</property>
		<relationship name="masterAssetFolder">
			<destination>{ae55c5b4-3504-4491-b1e4-d517b675087c}</destination>
		</relationship>
	</object>
</objects>
